{
  "legislative_session": "2025-2026",
  "identifier": "SB13",
  "title": "Eliminating requirements for filings, registrations and licenses related to labor organizations, educational facility agreements, annual tax reports, river bank easements and bonded warehousemen with the secretary of state.",
  "from_organization": "~{\"classification\": \"upper\"}",
  "classification": [
    "bill"
  ],
  "subject": [],
  "abstracts": [],
  "other_titles": [
    {
      "note": "",
      "title": "AN ACT concerning the secretary of state; relating to the filing of public records with the secretary of state; eliminating the requirement for labor organizations to file such organization's constitution, bylaws and annual reports and fees associated with such filings; eliminating requirements for the board of regents to file reciprocal agreements for use of educational facilities; eliminating the requirement for the secretary of revenue to file an annual report and lists of tax indebtedness and liabilities; eliminating the requirement that river bank easements be filed; eliminating requirements for warehousemen to be licensed by the secretary of state and for filing any associated records; amending K.S.A. 44-807, 44-809, 44-810, 44-823, 74-3220, 74-3221, 75-5501, 79-6a14, 79-3233g, 82-165 and 82-169 and K.S.A. 2024 Supp. 79-3233b and 82a-220 and repealing the existing sections; also repealing K.S.A. 44-805, 44-806, 44-806a, 75-4337, 82-163, 82-164 and 82-167."
    }
  ],
  "other_identifiers": [],
  "actions": [
    {
      "description": "Introduced",
      "date": "2025-01-16",
      "organization_id": "~{\"classification\": \"upper\"}",
      "classification": [
        "introduction"
      ],
      "related_entities": [],
      "_processing": {
        "log_file_created": "2025-10-24T23:29:36Z"
      }
    },
    {
      "description": "Referred to Committee on Government Efficiency",
      "date": "2025-01-17",
      "organization_id": "~{\"classification\": \"upper\"}",
      "classification": [
        "referral-committee"
      ],
      "related_entities": [],
      "_processing": {
        "log_file_created": "2025-10-24T23:29:36Z"
      }
    },
    {
      "description": "Hearing: Wednesday, January 29, 2025, 9:30 AM Room 144-S",
      "date": "2025-01-22",
      "organization_id": "~{\"classification\": \"upper\"}",
      "classification": [],
      "related_entities": [],
      "_processing": {
        "log_file_created": "2025-10-24T23:29:36Z"
      }
    },
    {
      "description": "Committee Report recommending bill be passed as amended by Committee on Government Efficiency",
      "date": "2025-02-06",
      "organization_id": "~{\"classification\": \"upper\"}",
      "classification": [
        "committee-passage-favorable"
      ],
      "related_entities": [],
      "_processing": {
        "log_file_created": "2025-10-24T23:29:36Z"
      }
    },
    {
      "description": "Committee of the Whole - Now working on",
      "date": "2025-02-18",
      "organization_id": "~{\"classification\": \"upper\"}",
      "classification": [],
      "related_entities": [],
      "_processing": {
        "log_file_created": "2025-10-24T23:29:36Z"
      }
    },
    {
      "description": "Committee of the Whole - Committee Report be adopted",
      "date": "2025-02-18",
      "organization_id": "~{\"classification\": \"upper\"}",
      "classification": [],
      "related_entities": [],
      "_processing": {
        "log_file_created": "2025-10-24T23:29:36Z"
      }
    },
    {
      "description": "Committee of the Whole - Be passed as amended",
      "date": "2025-02-18",
      "organization_id": "~{\"classification\": \"upper\"}",
      "classification": [
        "passage"
      ],
      "related_entities": [],
      "_processing": {
        "log_file_created": "2025-10-24T23:29:36Z"
      }
    },
    {
      "description": "Final Action - Passed as amended;  Yea: 40 Nay: 0",
      "date": "2025-02-19",
      "organization_id": "~{\"classification\": \"upper\"}",
      "classification": [
        "passage"
      ],
      "related_entities": [],
      "_processing": {
        "log_file_created": "2025-10-24T23:29:36Z"
      }
    },
    {
      "description": "Received and Introduced",
      "date": "2025-02-25",
      "organization_id": "~{\"classification\": \"lower\"}",
      "classification": [
        "introduction"
      ],
      "related_entities": [],
      "_processing": {
        "log_file_created": "2025-10-24T23:29:36Z"
      }
    },
    {
      "description": "Referred to Committee on Federal and State Affairs",
      "date": "2025-02-26",
      "organization_id": "~{\"classification\": \"lower\"}",
      "classification": [
        "referral-committee"
      ],
      "related_entities": [],
      "_processing": {
        "log_file_created": "2025-10-24T23:29:36Z"
      }
    },
    {
      "description": "Hearing: Tuesday, March 11, 2025, 9:00 AM Room 346-S",
      "date": "2025-03-05",
      "organization_id": "~{\"classification\": \"lower\"}",
      "classification": [],
      "related_entities": [],
      "_processing": {
        "log_file_created": "2025-10-24T23:29:36Z"
      }
    },
    {
      "description": "Committee Report recommending bill be passed by Committee on Federal and State Affairs",
      "date": "2025-03-18",
      "organization_id": "~{\"classification\": \"lower\"}",
      "classification": [
        "committee-passage-favorable"
      ],
      "related_entities": [],
      "_processing": {
        "log_file_created": "2025-10-24T23:29:36Z"
      }
    },
    {
      "description": "Committee of the Whole - Now working on",
      "date": "2025-03-19",
      "organization_id": "~{\"classification\": \"lower\"}",
      "classification": [],
      "related_entities": [],
      "_processing": {
        "log_file_created": "2025-10-24T23:29:36Z"
      }
    },
    {
      "description": "Committee of the Whole - Be passed",
      "date": "2025-03-19",
      "organization_id": "~{\"classification\": \"lower\"}",
      "classification": [
        "passage"
      ],
      "related_entities": [],
      "_processing": {
        "log_file_created": "2025-10-24T23:29:36Z"
      }
    },
    {
      "description": "Emergency Final Action - Passed;   Yea: 121 Nay: 2",
      "date": "2025-03-19",
      "organization_id": "~{\"classification\": \"lower\"}",
      "classification": [
        "passage"
      ],
      "related_entities": [],
      "_processing": {
        "log_file_created": "2025-10-24T23:29:36Z"
      }
    },
    {
      "description": "Enrolled and presented to Governor on Tuesday, March 25, 2025",
      "date": "2025-03-25",
      "organization_id": "~{\"classification\": \"upper\"}",
      "classification": [
        "executive-receipt"
      ],
      "related_entities": [],
      "_processing": {
        "log_file_created": "2025-10-24T23:29:36Z"
      }
    },
    {
      "description": "Approved by Governor on Tuesday, April 1, 2025",
      "date": "2025-04-10",
      "organization_id": "~{\"classification\": \"upper\"}",
      "classification": [
        "executive-signature"
      ],
      "related_entities": [],
      "_processing": {
        "log_file_created": "2025-10-24T23:29:36Z"
      }
    }
  ],
  "sponsorships": [],
  "related_bills": [],
  "versions": [
    {
      "note": "As introduced",
      "links": [
        {
          "url": "http://www.kslegislature.gov/li/b2025_26/measures/documents/sb13_00_0000.pdf",
          "media_type": "application/pdf"
        }
      ],
      "date": "",
      "classification": ""
    },
    {
      "note": "As Amended by Senate Committee",
      "links": [
        {
          "url": "http://www.kslegislature.gov/li/b2025_26/measures/documents/sb13_01_0000.pdf",
          "media_type": "application/pdf"
        }
      ],
      "date": "",
      "classification": ""
    },
    {
      "note": "Enrolled",
      "links": [
        {
          "url": "http://www.kslegislature.gov/li/b2025_26/measures/documents/sb13_enrolled.pdf",
          "media_type": "application/pdf"
        }
      ],
      "date": "",
      "classification": ""
    }
  ],
  "documents": [
    {
      "note": "As introduced Fiscal Note",
      "links": [
        {
          "url": "http://www.kslegislature.gov/li/b2025_26/measures/documents/fisc_note_sb13_00_0000.pdf",
          "media_type": "application/pdf"
        }
      ],
      "date": "",
      "classification": ""
    },
    {
      "note": "As Amended by Senate Committee Supp Note",
      "links": [
        {
          "url": "http://www.kslegislature.gov/li/b2025_26/measures/documents/supp_note_sb13_01_0000.pdf",
          "media_type": "application/pdf"
        }
      ],
      "date": "",
      "classification": ""
    }
  ],
  "citations": [],
  "sources": [
    {
      "url": "https://www.kslegislature.org/li/api/v12/rev-1/bill_status/SB13/",
      "note": ""
    },
    {
      "url": "http://kslegislature.org/li/b2025_26/measures/sb13/",
      "note": ""
    }
  ],
  "extras": {
    "status": "enacted"
  },
  "jurisdiction": {
    "id": "ocd-jurisdiction/country:us/state:ks/government",
    "name": "Kansas",
    "classification": "state",
    "division_id": "ocd-division/country:us/state:ks"
  },
  "_processing": {
    "logs_latest_update": "2025-10-24T23:29:36Z"
  }
}