{
  "legislative_session": "2025-2026",
  "identifier": "HB2241",
  "title": "Prohibiting second and successive motions and ineffective counsel claims in habeas corpus actions and providing for direct appeal to the supreme court in habeas corpus appeals filed by inmates sentenced to death.",
  "from_organization": "~{\"classification\": \"lower\"}",
  "classification": [
    "bill"
  ],
  "subject": [],
  "abstracts": [],
  "other_titles": [
    {
      "note": "",
      "title": "AN ACT concerning civil procedure; relating to habeas corpus; prohibiting second and successive motions in certain circumstances; prohibiting claims of ineffective counsel; providing appeals to the supreme court as a matter of right in claims filed by inmates sentenced to death; amending K.S.A. 2024 Supp. 60-1507 and 60-2102 and repealing the existing sections."
    }
  ],
  "other_identifiers": [],
  "actions": [
    {
      "description": "Introduced",
      "date": "2025-02-04",
      "organization_id": "~{\"classification\": \"lower\"}",
      "classification": [
        "introduction"
      ],
      "related_entities": [],
      "_processing": {
        "log_file_created": "2025-10-24T23:29:35Z"
      }
    },
    {
      "description": "Referred to Committee on Judiciary",
      "date": "2025-02-05",
      "organization_id": "~{\"classification\": \"lower\"}",
      "classification": [
        "referral-committee"
      ],
      "related_entities": [],
      "_processing": {
        "log_file_created": "2025-10-24T23:29:35Z"
      }
    }
  ],
  "sponsorships": [],
  "related_bills": [],
  "versions": [
    {
      "note": "As introduced",
      "links": [
        {
          "url": "http://www.kslegislature.gov/li/b2025_26/measures/documents/hb2241_00_0000.pdf",
          "media_type": "application/pdf"
        }
      ],
      "date": "",
      "classification": ""
    }
  ],
  "documents": [
    {
      "note": "As introduced Fiscal Note",
      "links": [
        {
          "url": "http://www.kslegislature.gov/li/b2025_26/measures/documents/fisc_note_hb2241_00_0000.pdf",
          "media_type": "application/pdf"
        }
      ],
      "date": "",
      "classification": ""
    }
  ],
  "citations": [],
  "sources": [
    {
      "url": "https://www.kslegislature.org/li/api/v12/rev-1/bill_status/HB2241/",
      "note": ""
    },
    {
      "url": "http://kslegislature.org/li/b2025_26/measures/hb2241/",
      "note": ""
    }
  ],
  "extras": {
    "status": "introduced"
  },
  "jurisdiction": {
    "id": "ocd-jurisdiction/country:us/state:ks/government",
    "name": "Kansas",
    "classification": "state",
    "division_id": "ocd-division/country:us/state:ks"
  },
  "_processing": {
    "logs_latest_update": "2025-10-24T23:29:35Z",
    "text_extraction_latest_update": "2025-10-25T04:23:15.649882Z"
  }
}