{
  "legislative_session": "2025-2026",
  "identifier": "SB144",
  "title": "Invalidating restrictive covenants that limit or prohibit the installation of solar panels and allowing the adoption of reasonable rules by homeowners associations concerning solar panels.",
  "from_organization": "~{\"classification\": \"upper\"}",
  "classification": [
    "bill"
  ],
  "subject": [],
  "abstracts": [],
  "other_titles": [
    {
      "note": "",
      "title": "AN ACT concerning real property; declaring current restrictive covenants that limit or prohibit the installation of solar panels on the rooftops of residential properties to be void and unenforceable; allowing homeowners associations to adopt reasonable rules concerning solar panels that do not prohibit rooftop installation."
    }
  ],
  "other_identifiers": [],
  "actions": [
    {
      "description": "Introduced",
      "date": "2025-02-03",
      "organization_id": "~{\"classification\": \"upper\"}",
      "classification": [
        "introduction"
      ],
      "related_entities": [],
      "_processing": {
        "log_file_created": "2025-10-24T23:29:35Z"
      }
    },
    {
      "description": "Referred to Committee on Local Government, Transparency and Ethics",
      "date": "2025-02-04",
      "organization_id": "~{\"classification\": \"upper\"}",
      "classification": [
        "referral-committee"
      ],
      "related_entities": [],
      "_processing": {
        "log_file_created": "2025-10-24T23:29:35Z"
      }
    }
  ],
  "sponsorships": [],
  "related_bills": [],
  "versions": [
    {
      "note": "As introduced",
      "links": [
        {
          "url": "http://www.kslegislature.gov/li/b2025_26/measures/documents/sb144_00_0000.pdf",
          "media_type": "application/pdf"
        }
      ],
      "date": "",
      "classification": ""
    }
  ],
  "documents": [
    {
      "note": "As introduced Fiscal Note",
      "links": [
        {
          "url": "http://www.kslegislature.gov/li/b2025_26/measures/documents/fisc_note_sb144_00_0000.pdf",
          "media_type": "application/pdf"
        }
      ],
      "date": "",
      "classification": ""
    }
  ],
  "citations": [],
  "sources": [
    {
      "url": "https://www.kslegislature.org/li/api/v12/rev-1/bill_status/SB144/",
      "note": ""
    },
    {
      "url": "http://kslegislature.org/li/b2025_26/measures/sb144/",
      "note": ""
    }
  ],
  "extras": {
    "status": "introduced"
  },
  "jurisdiction": {
    "id": "ocd-jurisdiction/country:us/state:ks/government",
    "name": "Kansas",
    "classification": "state",
    "division_id": "ocd-division/country:us/state:ks"
  },
  "_processing": {
    "logs_latest_update": "2025-10-24T23:29:35Z",
    "text_extraction_latest_update": "2025-10-25T04:39:02.267344Z"
  }
}